confettii/CHANGELOG.md
confettii/__about__.py
confettii/__init__.py
confettii/entropy_helper.py
confettii/feat_extract.py
confettii/ncc_helper.py
confettii/plot_helper.py
confettii/read_ims.py
confettii/rescale_helper.py
confettii-1.3.0.dist-info/METADATA
confettii-1.3.0.dist-info/WHEEL
confettii-1.3.0.dist-info/licenses/LICENSE.txt
confettii-1.3.0.dist-info/RECORD
