Metadata-Version: 2.3
Name: confettii
Version: 1.3.0
Project-URL: Documentation, https://github.com/U.N. Owen/confettii#readme
Project-URL: Issues, https://github.com/U.N. Owen/confettii/issues
Project-URL: Source, https://github.com/U.N. Owen/confettii
Author-email: "U.N. Owen" <void@some.where>
License: MIT
Classifier: Development Status :: 4 - Beta
Classifier: Programming Language :: Python
Classifier: Programming Language :: Python :: 3.8
Classifier: Programming Language :: Python :: 3.9
Classifier: Programming Language :: Python :: 3.10
Classifier: Programming Language :: Python :: 3.11
Classifier: Programming Language :: Python :: 3.12
Classifier: Programming Language :: Python :: Implementation :: CPython
Classifier: Programming Language :: Python :: Implementation :: PyPy
Requires-Python: >=3.8
Requires-Dist: h5py>=3.12.1
Requires-Dist: matplotlib>=3.9.2
Requires-Dist: numpy>=1.21
Requires-Dist: tifffile>=2023.2.28
